mcp_gsc/__init__.py
mcp_gsc/__main__.py
mcp_gsc-0.1.0.dist-info/METADATA
mcp_gsc-0.1.0.dist-info/WHEEL
mcp_gsc-0.1.0.dist-info/entry_points.txt
mcp_gsc-0.1.0.dist-info/top_level.txt
mcp_gsc-0.1.0.dist-info/RECORD
