Metadata-Version: 2.4
Name: mcp-gsc
Version: 0.1.0
Summary: Google Search Console integration for Model Context Protocol (MCP)
Author-email: Amin Foroutan <aio@aminforoutan.com>
License: MIT
Project-URL: Homepage, https://github.com/aminfseo/mcp-gsc
Project-URL: Bug Tracker, https://github.com/aminfseo/mcp-gsc/issues
Keywords: mcp,google search console,seo,claude,search analytics
Classifier: Development Status :: 4 - Beta
Classifier: Intended Audience :: Developers
Classifier: License :: OSI Approved :: MIT License
Classifier: Programming Language :: Python :: 3
Classifier: Programming Language :: Python :: 3.11
Classifier: Topic :: Internet :: WWW/HTTP :: Indexing/Search
Classifier: Topic :: Software Development :: Libraries :: Python Modules
Requires-Python: >=3.11
Requires-Dist: google-api-python-client>=2.163.0
Requires-Dist: google-auth-httplib2>=0.2.0
Requires-Dist: google-auth-oauthlib>=1.2.1
Requires-Dist: mcp[cli]>=1.3.0
